setup.cfg
setup.py
cppbuildprofiler/__init__.py
cppbuildprofiler/analysis.py
cppbuildprofiler/cli.py
cppbuildprofiler/dependency.py
cppbuildprofiler/parser.py
cppbuildprofiler/profiler.py
cppbuildprofiler.egg-info/PKG-INFO
cppbuildprofiler.egg-info/SOURCES.txt
cppbuildprofiler.egg-info/dependency_links.txt
cppbuildprofiler.egg-info/entry_points.txt
cppbuildprofiler.egg-info/requires.txt
cppbuildprofiler.egg-info/top_level.txt
test/test_analysis.py
test/test_cli.py
test/test_dependency.py
test/test_parser.py