Metadata-Version: 1.1
Name: cppbuildprofiler
Version: 0.4
Summary: A tool that facilitates profiling C++ builds.
Home-page: https://github.com/techland-games/cpp-build-profiler
Author: Mikolaj Radwan @ Techland
Author-email: mikolaj.radwan@techland.pl
License: MIT
Download-URL: https://github.com/techland-games/cpp-build-profiler/archive/0.1.tar.gz
Keywords: c++,building,compilation,profiling,optimisation
Platform: UNKNOWN
